{"cameraMode":{"drawMode":0,"name":"Shaded","section":"Shading Mode"},"sceneLighting":true,"audioPlay":false,"sceneViewState":{"m_AlwaysRefresh":false,"showFog":true,"showSkybox":true,"showFlares":true,"showImageEffects":true,"showParticleSystems":true,"showVisualEffectGraphs":true,"m_FxEnabled":true},"in2DMode":false,"pivot":{"x":39.4434700012207,"y":33.531715393066409,"z":1.811044692993164},"rotation":{"x":0.16724801063537599,"y":0.6056872606277466,"z":-0.13215559720993043,"w":0.7665897011756897},"size":28.760133743286134,"orthographic":false}